<?xml version="1.0" encoding="UTF-8"?>
<objects serializationModel="Studio.02.01.00">
	<object class="AudioFile" id="{ce766032-35ea-4b22-adfa-064bcf0bab8b}">
		<property name="assetPath">
			<value>PesadillaAbsorb.ogg</value>
		</property>
		<property name="frequencyInKHz">
			<value>44.0999985</value>
		</property>
		<property name="channelCount">
			<value>2</value>
		</property>
		<property name="length">
			<value>6.2948979591836736</value>
		</property>
		<relationship name="masterAssetFolder">
			<destination>{aa9c0f89-c0ef-44b6-b06f-468225cddf42}</destination>
		</relationship>
	</object>
</objects>
